tests/__init__.py
tests/test_ngram.py
thaitextgenerator/__init__.py
thaitextgenerator/thai2fit.py
thaitextgenerator/corpus/__init__.py
ttg-0.1.dev3.dist-info/LICENSE
ttg-0.1.dev3.dist-info/METADATA
ttg-0.1.dev3.dist-info/WHEEL
ttg-0.1.dev3.dist-info/top_level.txt
ttg-0.1.dev3.dist-info/RECORD
