Metadata-Version: 2.1
Name: ttg
Version: 0.1.dev3
Summary: Thai Text Generator library
Home-page: https://github.com/pythainlp/Thai-Text-Generator
Author: Wannaphong Phatthiyaphaibun
Author-email: wannaphong@kkumail.com
License: Apache Software License 2.0
Keywords: NLP,natural language processing,text analytics,text processing,localization,computational linguistics,ThaiNLP,Thai NLP,Thai language
Platform: UNKNOWN
Classifier: Development Status :: 5 - Production/Stable
Classifier: Programming Language :: Python :: 3
Classifier: Intended Audience :: Developers
Classifier: License :: OSI Approved :: Apache Software License
Classifier: Natural Language :: Thai
Classifier: Topic :: Scientific/Engineering :: Artificial Intelligence
Classifier: Topic :: Text Processing
Classifier: Topic :: Text Processing :: General
Classifier: Topic :: Text Processing :: Linguistic
Requires-Python: >=3.6
Requires-Dist: tqdm
Requires-Dist: requests
Provides-Extra: thai2fit
Requires-Dist: pythainlp (>=2.1) ; extra == 'thai2fit'
Requires-Dist: fastai ; extra == 'thai2fit'
Requires-Dist: pandas ; extra == 'thai2fit'
Requires-Dist: emoji (>=0.5.1) ; extra == 'thai2fit'
Requires-Dist: gensim (>=3.2.0) ; extra == 'thai2fit'
Requires-Dist: numpy (>=1.16.1) ; extra == 'thai2fit'
